infi.blocking-0.0.5-py2.7-nspkg.pth
infi/blocking/__init__.py
infi/blocking/__version__.py
infi/blocking/gevent_rpc.py
infi/blocking/rpc.py
infi/blocking/tests.py
infi/blocking/worker.py
infi/blocking/worker_process.py
infi.blocking-0.0.5.dist-info/LICENSE
infi.blocking-0.0.5.dist-info/METADATA
infi.blocking-0.0.5.dist-info/WHEEL
infi.blocking-0.0.5.dist-info/entry_points.txt
infi.blocking-0.0.5.dist-info/namespace_packages.txt
infi.blocking-0.0.5.dist-info/top_level.txt
infi.blocking-0.0.5.dist-info/RECORD
