Metadata-Version: 2.1
Name: infi.blocking
Version: 0.0.5
Summary: run blocking code in seprate process
Home-page: https://git.infinidat.com/host-opensource/infi.blocking
Author: Arnon Yaari
Author-email: arnony@infinidat.com
License: BSD
Platform: UNKNOWN
Classifier: Intended Audience :: Developers
Classifier: Intended Audience :: System Administrators
Classifier: License :: OSI Approved :: BSD License
Classifier: Operating System :: OS Independent
Classifier: Programming Language :: Python
Classifier: Programming Language :: Python :: 2
Classifier: Programming Language :: Python :: 3
Classifier: Topic :: Software Development :: Libraries :: Python Modules
Requires-Dist: infi.execute
Requires-Dist: infi.traceback
Requires-Dist: mprpc
Requires-Dist: msgpack-rpc-python
Requires-Dist: setuptools
Requires-Dist: six
Requires-Dist: tblib
Provides-Extra: gevent_rpc
Requires-Dist: mprpc; extra == 'gevent_rpc'
